{"ProjectBreakpoints":"{\"Value\":{},\"CodeBreakpoints\":{}}","Compiler":"2","ProjectWatches":"{\"Value\":[]}","OpenedDocuments":"[{\"DocumentPath\":\"Main.xaml\",\"FactoryId\":\"{ACB8E7BA-F093-44C1-9B50-33ECA51AAE16}\"}]","ProjectActivitiesViewState":"{\"Chrome-Udemy/Udemy_SearchCourses.xaml\":[{\"ActivityIdRef\":\"NTypeInto_1\",\"IsAdvancedOptionsExpanded\":false,\"Categories\":{\"Timings\":true,\"Options - Offset point\":true,\"Verify execution\":true,\"Input/Output\":true,\"Options\":true,\"Target\":true},\"Widgets\":{}},{\"ActivityIdRef\":\"NApplicationCard_1\",\"IsAdvancedOptionsExpanded\":false,\"Categories\":{\"Options\":true,\"Dialog Handling\":true,\"Timings\":true,\"Target application\":true,\"Input/Output\":true},\"Widgets\":{\"OCREngine\":{\"ShowExpanded\":true},\"Body\":{\"ShowExpanded\":true}}},{\"ActivityIdRef\":\"NClick_1\",\"IsAdvancedOptionsExpanded\":false,\"Categories\":{\"Timings\":true,\"Options - Offset point\":true,\"Options\":true,\"Input/Output\":true,\"Target\":true},\"Widgets\":{}},{\"ActivityIdRef\":\"LogMessage_1\",\"IsAdvancedOptionsExpanded\":false,\"Widgets\":{}},{\"ActivityIdRef\":\"LogMessage_2\",\"IsAdvancedOptionsExpanded\":false,\"Widgets\":{}},{\"ActivityIdRef\":\"NCheckState_1\",\"IsAdvancedOptionsExpanded\":false,\"Categories\":{\"Timings\":true,\"Input/Output\":true,\"Options\":true,\"Target\":true},\"Widgets\":{\"IfExists\":{\"ShowExpanded\":true},\"IfNotExists\":{\"ShowExpanded\":true}}},{\"ActivityIdRef\":\"LogMessage_3\",\"IsAdvancedOptionsExpanded\":false,\"Widgets\":{}}],\"Chrome-Udemy/Udemy_LaunchApp.xaml\":[{\"ActivityIdRef\":\"NApplicationCard_1\",\"IsAdvancedOptionsExpanded\":false,\"Categories\":{\"Options\":true,\"Dialog Handling\":true,\"Timings\":true,\"Target application\":true,\"Input/Output\":true},\"Widgets\":{\"OCREngine\":{\"ShowExpanded\":true},\"Body\":{\"ShowExpanded\":true}}},{\"ActivityIdRef\":\"LogMessage_1\",\"IsAdvancedOptionsExpanded\":false,\"Widgets\":{}},{\"ActivityIdRef\":\"LogMessage_2\",\"IsAdvancedOptionsExpanded\":false,\"Widgets\":{}}],\"Main.xaml\":[{\"ActivityIdRef\":\"LogMessage_1\",\"IsAdvancedOptionsExpanded\":false,\"Widgets\":{}},{\"ActivityIdRef\":\"InvokeWorkflowFile_4\",\"IsAdvancedOptionsExpanded\":false,\"Categories\":{\"Common\":true,\"Options\":true,\"Log\":true,\"Output\":true},\"Widgets\":{}},{\"ActivityIdRef\":\"MessageBox_1\",\"IsAdvancedOptionsExpanded\":false,\"Categories\":{\"Input\":true,\"Misc\":true,\"Output\":true},\"Widgets\":{}},{\"ActivityIdRef\":\"InvokeWorkflowFile_16\",\"IsAdvancedOptionsExpanded\":false,\"Categories\":{\"Common\":true,\"Options\":true,\"Log\":true},\"Widgets\":{}},{\"ActivityIdRef\":\"InvokeWorkflowFile_1\",\"IsAdvancedOptionsExpanded\":false,\"Categories\":{\"Common\":true,\"Options\":true,\"Log\":true},\"Widgets\":{}},{\"ActivityIdRef\":\"InvokeWorkflowFile_13\",\"IsAdvancedOptionsExpanded\":false,\"Categories\":{\"Common\":true,\"Options\":true,\"Log\":true},\"Widgets\":{}},{\"ActivityIdRef\":\"Assign_1\",\"IsAdvancedOptionsExpanded\":false,\"Widgets\":{}},{\"ActivityIdRef\":\"InvokeWorkflowFile_8\",\"IsAdvancedOptionsExpanded\":false,\"Categories\":{\"Common\":true,\"Options\":true,\"Log\":true},\"Widgets\":{}},{\"ActivityIdRef\":\"InvokeWorkflowFile_12\",\"IsAdvancedOptionsExpanded\":false,\"Categories\":{\"Common\":true,\"Options\":true,\"Log\":true},\"Widgets\":{}},{\"ActivityIdRef\":\"InvokeWorkflowFile_11\",\"IsAdvancedOptionsExpanded\":false,\"Categories\":{\"Common\":true,\"Options\":true,\"Log\":true},\"Widgets\":{}},{\"ActivityIdRef\":\"InvokeWorkflowFile_10\",\"IsAdvancedOptionsExpanded\":false,\"Categories\":{\"Common\":true,\"Options\":true,\"Log\":true},\"Widgets\":{}},{\"ActivityIdRef\":\"InvokeWorkflowFile_9\",\"IsAdvancedOptionsExpanded\":false,\"Categories\":{\"Common\":true,\"Options\":true,\"Log\":true},\"Widgets\":{}},{\"ActivityIdRef\":\"InvokeWorkflowFile_7\",\"IsAdvancedOptionsExpanded\":false,\"Categories\":{\"Common\":true,\"Options\":true,\"Log\":true},\"Widgets\":{}},{\"ActivityIdRef\":\"InvokeWorkflowFile_25\",\"IsAdvancedOptionsExpanded\":false,\"Categories\":{\"Common\":true,\"Options\":true,\"Log\":true,\"Output\":true},\"Widgets\":{}},{\"ActivityIdRef\":\"InvokeWorkflowFile_30\",\"IsAdvancedOptionsExpanded\":false,\"Categories\":{\"Common\":true,\"Options\":true,\"Log\":true},\"Widgets\":{}},{\"ActivityIdRef\":\"InvokeWorkflowFile_26\",\"IsAdvancedOptionsExpanded\":false,\"Categories\":{\"Common\":true,\"Options\":true,\"Log\":true},\"Widgets\":{}},{\"ActivityIdRef\":\"InvokeWorkflowFile_14\",\"IsAdvancedOptionsExpanded\":false,\"Categories\":{\"Common\":true,\"Options\":true,\"Log\":true,\"Output\":true},\"Widgets\":{}},{\"ActivityIdRef\":\"InvokeWorkflowFile_15\",\"IsAdvancedOptionsExpanded\":false,\"Categories\":{\"Common\":true,\"Options\":true,\"Log\":true,\"Output\":true},\"Widgets\":{}},{\"ActivityIdRef\":\"InvokeWorkflowFile_28\",\"IsAdvancedOptionsExpanded\":false,\"Categories\":{\"Common\":true,\"Options\":true,\"Log\":true,\"Output\":true},\"Widgets\":{}},{\"ActivityIdRef\":\"InvokeWorkflowFile_29\",\"IsAdvancedOptionsExpanded\":false,\"Categories\":{\"Common\":true,\"Options\":true,\"Log\":true,\"Output\":true},\"Widgets\":{}}],\"Chrome-Udemy/Udemy_RetrieveCourseData.xaml\":[{\"ActivityIdRef\":\"NApplicationCard_5\",\"IsAdvancedOptionsExpanded\":false,\"Categories\":{\"Options\":true,\"Dialog Handling\":true,\"Timings\":true,\"Target application\":true,\"Input/Output\":true,\"Target\":true},\"Widgets\":{\"OCREngine\":{\"ShowExpanded\":true},\"Body\":{\"ShowExpanded\":true}}},{\"ActivityIdRef\":\"NClick_1\",\"IsAdvancedOptionsExpanded\":false,\"Categories\":{\"Timings\":true,\"Options - Offset point\":true,\"Options\":true,\"Input/Output\":true,\"Target\":true},\"Widgets\":{}},{\"ActivityIdRef\":\"NGetText_7\",\"IsAdvancedOptionsExpanded\":false,\"Categories\":{\"Timings\":true,\"Input/Output\":true,\"Options\":true,\"Target\":true},\"Widgets\":{}},{\"ActivityIdRef\":\"Assign_2\",\"IsAdvancedOptionsExpanded\":false,\"Widgets\":{}},{\"ActivityIdRef\":\"LogMessage_1\",\"IsAdvancedOptionsExpanded\":false,\"Widgets\":{}},{\"ActivityIdRef\":\"Assign_1\",\"IsAdvancedOptionsExpanded\":false,\"Widgets\":{}},{\"ActivityIdRef\":\"InterruptibleWhile_1\",\"IsAdvancedOptionsExpanded\":false,\"Categories\":{\"\":true},\"Widgets\":{\"Body\":{\"ShowExpanded\":true}}},{\"ActivityIdRef\":\"AddDataRow_1\",\"IsAdvancedOptionsExpanded\":false,\"Widgets\":{}},{\"ActivityIdRef\":\"NGetText_5\",\"IsAdvancedOptionsExpanded\":false,\"Categories\":{\"Timings\":true,\"Input/Output\":true,\"Options\":true,\"Target\":true},\"Widgets\":{}},{\"ActivityIdRef\":\"NGetText_6\",\"IsAdvancedOptionsExpanded\":false,\"Categories\":{\"Timings\":true,\"Input/Output\":true,\"Options\":true,\"Target\":true},\"Widgets\":{}},{\"ActivityIdRef\":\"NGetText_4\",\"IsAdvancedOptionsExpanded\":false,\"Categories\":{\"Timings\":true,\"Input/Output\":true,\"Options\":true,\"Target\":true},\"Widgets\":{}},{\"ActivityIdRef\":\"Assign_3\",\"IsAdvancedOptionsExpanded\":false,\"Widgets\":{}},{\"ActivityIdRef\":\"LogMessage_2\",\"IsAdvancedOptionsExpanded\":false,\"Widgets\":{}},{\"ActivityIdRef\":\"NApplicationCard_4\",\"IsAdvancedOptionsExpanded\":false,\"Categories\":{\"Options\":true,\"Dialog Handling\":true,\"Timings\":true,\"Target application\":true,\"Input/Output\":true,\"Target\":true},\"Widgets\":{\"OCREngine\":{\"ShowExpanded\":true},\"Body\":{\"ShowExpanded\":true}}}],\"Chrome-Udemy/Udemy_ShowLeastPriceCourses.xaml\":[{\"ActivityIdRef\":\"LogMessage_1\",\"IsAdvancedOptionsExpanded\":false,\"Widgets\":{}},{\"ActivityIdRef\":\"Assign_1\",\"IsAdvancedOptionsExpanded\":false,\"Widgets\":{}},{\"ActivityIdRef\":\"Assign_2\",\"IsAdvancedOptionsExpanded\":false,\"Widgets\":{}},{\"ActivityIdRef\":\"MessageBox_1\",\"IsAdvancedOptionsExpanded\":false,\"Categories\":{\"Input\":true,\"Misc\":true,\"Output\":true},\"Widgets\":{}},{\"ActivityIdRef\":\"LogMessage_2\",\"IsAdvancedOptionsExpanded\":false,\"Widgets\":{}}],\"NotePad/NotePad_SaveCoursesData.xaml\":[{\"ActivityIdRef\":\"LogMessage_1\",\"IsAdvancedOptionsExpanded\":false,\"Widgets\":{}},{\"ActivityIdRef\":\"OutputDataTable_1\",\"IsAdvancedOptionsExpanded\":false,\"Widgets\":{}},{\"ActivityIdRef\":\"Assign_1\",\"IsAdvancedOptionsExpanded\":false,\"Widgets\":{}},{\"ActivityIdRef\":\"WriteTextFile_2\",\"IsAdvancedOptionsExpanded\":false,\"Categories\":{\"Common\":true,\"File\":true,\"Output\":true},\"Widgets\":{}}],\"Control/Control_CheckToContinue.xaml\":[{\"ActivityIdRef\":\"MessageBox_1\",\"IsAdvancedOptionsExpanded\":false,\"Categories\":{\"Input\":true,\"Misc\":true,\"Output\":true},\"Widgets\":{}},{\"ActivityIdRef\":\"Assign_1\",\"IsAdvancedOptionsExpanded\":false,\"Widgets\":{}}],\"Chrome-Udemy/Udemy_CloseApp.xaml\":[{\"ActivityIdRef\":\"LogMessage_1\",\"IsAdvancedOptionsExpanded\":false,\"Widgets\":{}},{\"ActivityIdRef\":\"LogMessage_2\",\"IsAdvancedOptionsExpanded\":false,\"Widgets\":{}},{\"ActivityIdRef\":\"KillProcess_1\",\"IsAdvancedOptionsExpanded\":false,\"Categories\":{\"Target\":true,\"Common\":true},\"Widgets\":{}}]}"}